Metadata-Version: 2.1
Name: new-DisUtils
Version: 1.3.5
Summary: Dis-Utils is a very useful library made to be used with pycord.
Home-page: https://www.github.com/DTS-11/Dis-Utils
Author: DTS
License: UNKNOWN
Platform: UNKNOWN
Classifier: Programming Language :: Python :: 3
Classifier: License :: OSI Approved :: MIT License
Classifier: Operating System :: OS Independent
Requires-Python: >= 3.6
Provides-Extra: voice
License-File: LICENSE
